labgauth/__init__.py
labgauth/lab_adapter.py
labgauth/tests.py
labgauth/templates/admin/login.html
sandbox/__init__.py
sandbox/settings.py
sandbox/urls.py
sandbox/wsgi.py
thelab_gauth-0.1.1.dist-info/DESCRIPTION.rst
thelab_gauth-0.1.1.dist-info/METADATA
thelab_gauth-0.1.1.dist-info/RECORD
thelab_gauth-0.1.1.dist-info/WHEEL
thelab_gauth-0.1.1.dist-info/metadata.json
thelab_gauth-0.1.1.dist-info/top_level.txt
