Metadata-Version: 2.0
Name: thelab-gauth
Version: 0.1.1
Summary: Mostly drop in django app to use Google Apps for thelab users.
Home-page: https://gitlab.com/thelabnyc/thelab-gauth
Author: UNKNOWN
Author-email: dburke@thelabnyc.com
License: Apache License
Platform: UNKNOWN
Classifier: Development Status :: 3 - Alpha
Classifier: Environment :: Web Environment
Classifier: Framework :: Django
Classifier: Framework :: Django :: 1.11
Classifier: Framework :: Django :: 1.10
Classifier: Framework :: Django :: 1.8
Classifier: Intended Audience :: Developers
Classifier: Natural Language :: English
Classifier: Operating System :: Unix
Classifier: Programming Language :: Python
Classifier: Programming Language :: Python :: 3
Classifier: Topic :: Software Development :: Libraries :: Python Modules
Requires-Dist: Django (>=1.9.6)
Requires-Dist: django-allauth (>=0.32.0)
